miscnn/__init__.py
miscnn/cli/__init__.py
miscnn/cli/__main__.py
miscnn/cli/data_exploration.py
miscnn/data_loading/__init__.py
miscnn/data_loading/data_io.py
miscnn/data_loading/sample.py
miscnn/data_loading/interfaces/__init__.py
miscnn/data_loading/interfaces/abstract_io.py
miscnn/data_loading/interfaces/dicom_io.py
miscnn/data_loading/interfaces/dictionary_io.py
miscnn/data_loading/interfaces/image_io.py
miscnn/data_loading/interfaces/nifti_io.py
miscnn/data_loading/interfaces/nifti_slicer_io.py
miscnn/ensembler/__init__.py
miscnn/ensembler/mean.py
miscnn/evaluation/__init__.py
miscnn/evaluation/cross_validation.py
miscnn/evaluation/detailed_validation.py
miscnn/evaluation/leave_one_out.py
miscnn/evaluation/split_validation.py
miscnn/multi_model/__init__.py
miscnn/multi_model/cross_validation_group.py
miscnn/multi_model/model.py
miscnn/multi_model/model_group.py
miscnn/neural_network/__init__.py
miscnn/neural_network/data_generator.py
miscnn/neural_network/metrics.py
miscnn/neural_network/model.py
miscnn/neural_network/architecture/__init__.py
miscnn/neural_network/architecture/abstract_architecture.py
miscnn/neural_network/architecture/unet/__init__.py
miscnn/neural_network/architecture/unet/attention.py
miscnn/neural_network/architecture/unet/attention_residual.py
miscnn/neural_network/architecture/unet/compact.py
miscnn/neural_network/architecture/unet/dense.py
miscnn/neural_network/architecture/unet/multiRes.py
miscnn/neural_network/architecture/unet/plain.py
miscnn/neural_network/architecture/unet/residual.py
miscnn/neural_network/architecture/unet/standard.py
miscnn/processing/__init__.py
miscnn/processing/batch_creation.py
miscnn/processing/data_augmentation.py
miscnn/processing/preprocessor.py
miscnn/processing/subfunctions/__init__.py
miscnn/processing/subfunctions/abstract_subfunction.py
miscnn/processing/subfunctions/clipping.py
miscnn/processing/subfunctions/normalization.py
miscnn/processing/subfunctions/padding.py
miscnn-1.4.0.dist-info/LICENSE.md
miscnn-1.4.0.dist-info/METADATA
miscnn-1.4.0.dist-info/WHEEL
miscnn-1.4.0.dist-info/top_level.txt
miscnn-1.4.0.dist-info/RECORD
