Metadata-Version: 2.1
Name: miscnn
Version: 1.4.0
Summary: Framework for Medical Image Segmentation with Convolutional Neural Networks and Deep Learning
Home-page: https://github.com/frankkramer-lab/MIScnn
Author: Dominik Müller
Author-email: dominik.mueller@informatik.uni-augsburg.de
License: GPLv3
Platform: UNKNOWN
Classifier: Programming Language :: Python :: 3
Classifier: Programming Language :: Python :: 3.7
Classifier: Programming Language :: Python :: 3.8
Classifier: License :: OSI Approved :: GNU General Public License v3 (GPLv3)
Classifier: Operating System :: OS Independent
Classifier: Intended Audience :: Healthcare Industry
Classifier: Intended Audience :: Science/Research
Classifier: Topic :: Scientific/Engineering :: Artificial Intelligence
Classifier: Topic :: Scientific/Engineering :: Image Recognition
Classifier: Topic :: Scientific/Engineering :: Medical Science Apps.
Requires-Python: >=3.7
Requires-Dist: tensorflow (==2.7.0)
Requires-Dist: tensorflow-addons (==0.15.0)
Requires-Dist: numpy (==1.19.2)
Requires-Dist: pandas (>=1.1.4)
Requires-Dist: tqdm (==4.51.0)
Requires-Dist: nibabel (>=3.1.0)
Requires-Dist: matplotlib (==3.3.1)
Requires-Dist: pillow (==8.3.2)
Requires-Dist: batchgenerators (==0.21)
Requires-Dist: pydicom (==2.0.0)
Requires-Dist: SimpleITK (==2.0.2)
Requires-Dist: scikit-image (==0.18.2)
